cnxpublishing/__init__.py
cnxpublishing/_version.py
cnxpublishing/authnz.py
cnxpublishing/bake.py
cnxpublishing/cache.py
cnxpublishing/celery.py
cnxpublishing/config.py
cnxpublishing/db.py
cnxpublishing/events.py
cnxpublishing/exceptions.py
cnxpublishing/main.py
cnxpublishing/publish.py
cnxpublishing/session.py
cnxpublishing/subscribers.py
cnxpublishing/tasks.py
cnxpublishing/utils.py
cnxpublishing/scripts/__init__.py
cnxpublishing/scripts/channel_processing.py
cnxpublishing/static/css/main.css
cnxpublishing/static/css/normalize.css
cnxpublishing/static/css/normalize.min.css
cnxpublishing/static/js/main.js
cnxpublishing/static/js/plugins.js
cnxpublishing/static/js/vendor/jquery-1.11.2.min.js
cnxpublishing/static/js/vendor/modernizr-2.8.3.min.js
cnxpublishing/tests/__init__.py
cnxpublishing/tests/conftest.py
cnxpublishing/tests/test_bake.py
cnxpublishing/tests/test_db.py
cnxpublishing/tests/test_doctests.py
cnxpublishing/tests/test_events.py
cnxpublishing/tests/test_publish.py
cnxpublishing/tests/test_subscribers.py
cnxpublishing/tests/test_utils.py
cnxpublishing/tests/testing.py
cnxpublishing/tests/use_cases.py
cnxpublishing/tests/data/85c441fc.png
cnxpublishing/tests/data/e3d625fe.png
cnxpublishing/tests/data/recipe_1.css
cnxpublishing/tests/data/recipe_2.css
cnxpublishing/tests/data/ruleset.css
cnxpublishing/tests/scripts/__init__.py
cnxpublishing/tests/scripts/test_channel_processing.py
cnxpublishing/tests/views/__init__.py
cnxpublishing/tests/views/base.py
cnxpublishing/tests/views/test_admin.py
cnxpublishing/tests/views/test_api_keys.py
cnxpublishing/tests/views/test_publishing.py
cnxpublishing/tests/views/test_user_actions.py
cnxpublishing/views/__init__.py
cnxpublishing/views/api_keys.py
cnxpublishing/views/common.py
cnxpublishing/views/moderation.py
cnxpublishing/views/publishing.py
cnxpublishing/views/user_actions.py
cnxpublishing/views/admin/__init__.py
cnxpublishing/views/admin/content_status.py
cnxpublishing/views/admin/index.py
cnx_publishing-0.17.32.dist-info/LICENSE.txt
cnx_publishing-0.17.32.dist-info/METADATA
cnx_publishing-0.17.32.dist-info/WHEEL
cnx_publishing-0.17.32.dist-info/entry_points.txt
cnx_publishing-0.17.32.dist-info/top_level.txt
cnx_publishing-0.17.32.dist-info/RECORD
