Metadata-Version: 2.1
Name: cnx-publishing
Version: 0.17.32
Summary: Application for accepting publication requests to the Connexions Archive.
Home-page: https://github.com/connexions/cnx-publishing
Author: Connexions team
Author-email: info@cnx.org
License: LGPL, See also LICENSE.txt
Platform: UNKNOWN
Requires-Dist: amqp (==2.6.1)
Requires-Dist: appdirs (==1.4.4)
Requires-Dist: Beaker (==1.11.0)
Requires-Dist: billiard (==3.6.4.0)
Requires-Dist: celery (==4.4.7)
Requires-Dist: certifi (==2021.5.30)
Requires-Dist: chardet (==4.0.0)
Requires-Dist: cnx-archive (==4.15.23)
Requires-Dist: cnx-common (==1.3.6)
Requires-Dist: cnx-db (==3.5.3)
Requires-Dist: cnx-easybake (==1.2.7)
Requires-Dist: cnx-epub (==0.26.2)
Requires-Dist: cnx-query-grammar (==0.2.2)
Requires-Dist: cnx-recipes (>=1.45.0)
Requires-Dist: cnx-transforms (==1.2.2)
Requires-Dist: cssselect (==1.1.0)
Requires-Dist: cnx-cssselect2 (==0.2.3)
Requires-Dist: db-migrator (==1.1.0)
Requires-Dist: funcsigs (==1.0.2)
Requires-Dist: future (==0.18.2)
Requires-Dist: hupper (==1.10.3)
Requires-Dist: idna (==2.10)
Requires-Dist: Jinja2 (==2.11.3)
Requires-Dist: kombu (==4.6.11)
Requires-Dist: lxml (==4.4.3)
Requires-Dist: MarkupSafe (==1.1.1)
Requires-Dist: openstax-accounts (==1.0.0)
Requires-Dist: packaging (==20.9)
Requires-Dist: parsimonious (==0.8.1)
Requires-Dist: Paste (==3.5.0)
Requires-Dist: PasteDeploy (==2.1.1)
Requires-Dist: PasteScript (==3.2.1)
Requires-Dist: plaster (==1.0)
Requires-Dist: plaster-pastedeploy (==0.7)
Requires-Dist: psycopg2 (==2.8.6)
Requires-Dist: PyICU (==2.7.4)
Requires-Dist: pyparsing (==2.4.7)
Requires-Dist: pyramid (==1.10.7)
Requires-Dist: pyramid-jinja2 (==2.8)
Requires-Dist: pyramid-multiauth (==0.9.0)
Requires-Dist: pyramid-sawing (==1.1.3)
Requires-Dist: pyramid-translogger (==0.1)
Requires-Dist: python-memcached (==1.59)
Requires-Dist: pytz (==2021.1)
Requires-Dist: PyYAML (==5.4.1)
Requires-Dist: repoze.lru (==0.7)
Requires-Dist: requests (==2.25.1)
Requires-Dist: rhaptos.cnxmlutils (==2.1.1)
Requires-Dist: sanction (==0.4.1)
Requires-Dist: six (==1.16.0)
Requires-Dist: SQLAlchemy (==1.4.20)
Requires-Dist: tinycss2 (==0.6.1)
Requires-Dist: translationstring (==1.4)
Requires-Dist: tzlocal (==2.1)
Requires-Dist: urllib3 (==1.26.6)
Requires-Dist: venusian (<2.0.0,>=1.2.0)
Requires-Dist: vine (==1.3.0)
Requires-Dist: waitress (==1.4.4)
Requires-Dist: webencodings (==0.5.1)
Requires-Dist: WebOb (==1.8.7)
Requires-Dist: zope.deprecation (==4.4.0)
Requires-Dist: zope.interface (==5.4.0)
Provides-Extra: test
Requires-Dist: pytest (==4.6.9) ; extra == 'test'
Requires-Dist: pytest-cov (==2.12.1) ; extra == 'test'
Requires-Dist: pytest-mock (==2.0.0) ; extra == 'test'
Requires-Dist: pytest-runner (==5.2) ; extra == 'test'
Requires-Dist: vcrpy-unittest (==0.1.7) ; extra == 'test'
Requires-Dist: webtest (==2.0.35) ; extra == 'test'
Requires-Dist: mock (==3.0.5) ; (python_version <= "2.7") and extra == 'test'
